img_converter/__init__.py
img_h5_converter-1.1.4.dist-info/METADATA
img_h5_converter-1.1.4.dist-info/WHEEL
img_h5_converter-1.1.4.dist-info/top_level.txt
img_h5_converter-1.1.4.dist-info/RECORD
