Metadata-Version: 2.1
Name: img_h5_converter
Version: 1.1.4
Summary: To convert an image to HDF5 file format which can be then sent and converted back to any of the image format.
Home-page: https://github.com/architmishra-15/Projects/tree/main/img_converter
Author: Archit Mishra
Classifier: Programming Language :: Python :: 3
Classifier: License :: OSI Approved :: MIT License
Classifier: Operating System :: OS Independent
Requires-Python: >=3.6
Requires-Dist: numpy
Requires-Dist: Pillow
Requires-Dist: h5py
